flask_fluence/__init__.py
flask_fluence/component.py
flask_fluence/jinja_ext.py
flask_fluence/render.py
flask_fluence/templates.py
flask_fluence/lib/__init__.py
flask_fluence/lib/names.py
flask_fluence-0.0.1.dist-info/METADATA
flask_fluence-0.0.1.dist-info/WHEEL
flask_fluence-0.0.1.dist-info/entry_points.txt
flask_fluence-0.0.1.dist-info/RECORD
